LICENSE
MANIFEST.in
README.md
setup.py
pycalibrate/__init__.py
pycalibrate/calibrate.py
pycalibrate/callbacks.py
pycalibrate/helpers.py
pycalibrate/reliabilitycurve.py
pycalibrate.egg-info/PKG-INFO
pycalibrate.egg-info/SOURCES.txt
pycalibrate.egg-info/dependency_links.txt
pycalibrate.egg-info/requires.txt
pycalibrate.egg-info/top_level.txt
pycalibrate/vis/dist/calibration.js