Metadata-Version: 2.1
Name: pycalibrate
Version: 0.0.3
Summary: pycalibrate. A tool to assess classifier calibration in Jupyter Notebooks
Home-page: https://github.com/VIDA-NYU/pycalibrate
Author: Peter Xenopoulos, Joao Rulff, Brian Barr, Luis Gustavo Nonato, Claudio Silva
Author-email: xenopoulos@nyu.edu
License: UNKNOWN
Platform: UNKNOWN
Classifier: Programming Language :: Python :: 3
Classifier: License :: OSI Approved :: BSD License
Classifier: Operating System :: OS Independent
Requires-Python: >=3.7
License-File: LICENSE
